<?xml version="1.0" encoding="UTF-8"?>
<objects serializationModel="Studio.02.02.00">
	<object class="AudioFile" id="{809413da-f7ea-4340-9b75-7902adb26c76}">
		<property name="assetPath">
			<value>Spells/Invoker/spell_sh_revamp_elementalblast_precast02.ogg</value>
		</property>
		<property name="frequencyInKHz">
			<value>44.0999985</value>
		</property>
		<property name="channelCount">
			<value>1</value>
		</property>
		<property name="length">
			<value>2.5278231292517006</value>
		</property>
		<relationship name="masterAssetFolder">
			<destination>{6d482be1-744e-4512-8cf4-a507dedf0b91}</destination>
		</relationship>
	</object>
</objects>
