<?xml version="1.0" encoding="UTF-8"?>
<objects serializationModel="Studio.02.02.00">
	<object class="AudioFile" id="{ff146bdc-d0f6-4837-8358-79090ba7a1e8}">
		<property name="assetPath">
			<value>Spells/Knight/Shield/fx_holy_magic_impact_medium_01.ogg</value>
		</property>
		<property name="frequencyInKHz">
			<value>22.0499992</value>
		</property>
		<property name="channelCount">
			<value>1</value>
		</property>
		<property name="length">
			<value>2.2935147392290252</value>
		</property>
		<relationship name="masterAssetFolder">
			<destination>{6d482be1-744e-4512-8cf4-a507dedf0b91}</destination>
		</relationship>
	</object>
</objects>
